tl_lab/__init__.py
tl_lab/exp.py
tl_lab-0.1.dist-info/METADATA
tl_lab-0.1.dist-info/WHEEL
tl_lab-0.1.dist-info/top_level.txt
tl_lab-0.1.dist-info/RECORD
