Metadata-Version: 2.4
Name: tl_lab
Version: 0.1
Summary: Collection of ML experiments as reusable package
Author: Your Name
Requires-Dist: tensorflow
Requires-Dist: matplotlib
Requires-Dist: kagglehub
Requires-Dist: opendatasets
Requires-Dist: scikit-learn
Requires-Dist: transformers
Requires-Dist: datasets
Requires-Dist: torch
Requires-Dist: seaborn
Dynamic: author
Dynamic: requires-dist
Dynamic: summary
